flex_blob/__init__.py
flex_blob/admin.py
flex_blob/apps.py
flex_blob/builders.py
flex_blob/fields.py
flex_blob/models.py
flex_blob/urls.py
flex_blob/utils.py
flex_blob/views.py
flex_blob/migrations/0001_initial.py
flex_blob/migrations/0002_filemodel_uploaded_at.py
flex_blob/migrations/__init__.py
django_flex_blob-0.0.13.dist-info/AUTHORS.rst
django_flex_blob-0.0.13.dist-info/LICENSE
django_flex_blob-0.0.13.dist-info/METADATA
django_flex_blob-0.0.13.dist-info/WHEEL
django_flex_blob-0.0.13.dist-info/top_level.txt
django_flex_blob-0.0.13.dist-info/RECORD
