Metadata-Version: 2.2
Name: django_flex_blob
Version: 0.0.13
Summary: A django app dedicated for managing media files and access to them
Author-email: Saman Zand Haghighi <samanzandh@gmail.com>, Ali Avani <ali.avani@outlook.com>
Maintainer-email: Saman Zand Haghighi <samanzandh@gmail.com>, Ali Avani <ali.avani@outlook.com>
License: MIT license
Project-URL: bugs, https://github.com/ali-avani/django_flex_blob/issues
Project-URL: changelog, https://github.com/ali-avani/django_flex_blob/blob/master/changelog.md
Project-URL: homepage, https://github.com/ali-avani/django_flex_blob
License-File: LICENSE
License-File: AUTHORS.rst
Provides-Extra: dev
Requires-Dist: coverage; extra == "dev"
Requires-Dist: mypy; extra == "dev"
Requires-Dist: pytest; extra == "dev"
Requires-Dist: ruff; extra == "dev"
